setup.py
rpmbrew/__init__.py
rpmbrew/brewlib.py
rpmbrew/rpmbrew.py
rpmbrew_tools.egg-info/PKG-INFO
rpmbrew_tools.egg-info/SOURCES.txt
rpmbrew_tools.egg-info/dependency_links.txt
rpmbrew_tools.egg-info/entry_points.txt
rpmbrew_tools.egg-info/requires.txt
rpmbrew_tools.egg-info/top_level.txt